[{
  "_id": {
    "$oid": "60651e9484b46a2e98f578fa"
  },
  "state": 0,
  "author": {
    "$oid": "6061eb606b08d82cc4c5697f"
  },
  "content": "文章很精彩啊啊啊",
  "post": {
    "$oid": "60646a715c596d1aacaf1aea"
  },
  "createAt": {
    "$date": "2021-04-01T06:51:20.552Z"
  }
},{
  "_id": {
    "$oid": "6065964a361eee094c22f8c4"
  },
  "state": 0,
  "content": "啊啊啊啊",
  "post": {
    "$oid": "60646b2a5c596d1aacaf1aec"
  },
  "author": {
    "$oid": "6061eb606b08d82cc4c5697f"
  },
  "createAt": {
    "$date": "2021-04-01T09:45:46.338Z"
  }
},{
  "_id": {
    "$oid": "606597536a6922259c3665b7"
  },
  "state": 0,
  "content": "dadasdasd",
  "post": {
    "$oid": "60646b6e5c596d1aacaf1af0"
  },
  "author": {
    "$oid": "6061f5c56b08d82cc4c56980"
  },
  "createAt": {
    "$date": "2021-04-01T09:50:11.656Z"
  }
}]